dayu_oiio/__init__.py
dayu_oiio/base.py
dayu_oiio/config.py
dayu_oiio/stream.py
dayu_oiio-0.2.dist-info/METADATA
dayu_oiio-0.2.dist-info/RECORD
dayu_oiio-0.2.dist-info/WHEEL
dayu_oiio-0.2.dist-info/top_level.txt
