Metadata-Version: 2.1
Name: dayu-oiio
Version: 0.2
Summary: a python wrapper for OpenImageIO oiiotool.
Home-page: https://github.com/phenom-films/dayu_oiio
Author: andyguo
Author-email: andyguo@phenom-films.com
License: MIT
Platform: UNKNOWN
Classifier: Operating System :: OS Independent
Classifier: Programming Language :: Python
Classifier: Programming Language :: Python :: Implementation
Classifier: Programming Language :: Python :: 2
Classifier: Programming Language :: Python :: 2.7
